{
  "success": true,
  "file": "..\\content\\JEE\\Previous Papers\\2023\\Session2\\Maths\\0604-Mathematics Paper Morning.pdf",
  "relativePath": "JEE\\Previous Papers\\2023\\Session2\\Maths\\0604-Mathematics Paper Morning.pdf",
  "metadata": {
    "originalFileName": "0604-Mathematics Paper Morning.pdf",
    "subject": "Mathematics",
    "year": 2023,
    "session": null,
    "shift": null,
    "paperType": "With Solution",
    "date": null,
    "fileType": "pdf",
    "totalPages": 8,
    "fileSize": 443206,
    "processedAt": "2025-09-22T23:53:06.453Z"
  },
  "content": {
    "originalText": "1 FINAL JEE–MAIN EXAMINATION – APRIL, 2023 (Held On Thursday 06\nth April, 2023) TIME : 9 : 00 AM to 12 : 00 NOON MATHEMATICS TEST PAPER WITH SOLUTION SECTION-A 1. Let ()\n11\n5f x 4f3,x 0\nxx\n\n\n\n+= + \n. Then (\n)\n2\n1\n18 f x dx\n is equal to: (1) 10 log\ne 2 – 6 (2) 10 log\ne 2 + 6 (3) 5 log\ne 2 + 3 (4) 5 log\ne 2 – 3 Official Ans. by NTA (1) Allen Ans. (1) Sol. (\n)\n11\n5f x 4f\n3\nxx\n\n\n\n+\n= +\n........(1) replace 1\nx\nx\n→ (\n)\n1\nx\nx\n5f\n4f\nx 3\n\n\n\n+\n= +\n......(2) Eq. (1) × 5 – eq. (2) × 4 15\nf(x)\n4x 3\n9x\n\n=\n− +\n\n I = 2\n1\n15\n18\n4x 3 dx\n9x\n\n−+\n\n\n = 10 log\ne 2 – 6 2. A pair of dice is thrown 5 times. For each throw, a total of 5 is considered a success. If the probability of at least 4 successes is 11\nk\n3\n,then k is equal to (1) 82 (2) 123 (3) 164 (4) 75 Official Ans. by NTA (2) Allen Ans. (2) Sol. Probability of success = 1\n9\n= p Probability of failure\n8\nq\n9\n= P(at least 4 success) = P (4 success) + P (5 success) = 5455\n45\n10\n41\nC p q C p\n3\n+=\n= 11\n123\n3 k = 123 3. If 2n\nn\n33\nC : C 10:1\n=\n, then the ratio (\n)\n(\n)\n22\nn\n3n : n – 3n 4\n++ is (1) 35: 16 (2) 65:37 (3) 27:11 (4) 2:1 Official Ans. by NTA (4) Allen Ans. (4) Sol. 2n\n3\nn\n3\nC\n10\nC\n=\n⇒ (\n)\n(\n)\n(\n)\n(\n)\n2n 2n 1 2n 2\n10\nn n 1 n 2\n−−\n=\n−− n = 8 So (\n)\n(\n)\n22\nn 3n : n – 3n 4\n2\n+\n+ = 4. If the ratio of the fifth term from the begining to the fifth term from the end in the expansion of n\n4\n4\n1\n2\n3\n\n+\n\n is 6 :1\n, then the third term from the beginning is: (1) 60 2 (2) 60 3 (3) 30 2 (4) 30 3 Official Ans. by NTA (2) Allen Ans. (2) Sol. 4\nn 4\n1\nn\n44\n4\n4\nn4\n1\nn\n4\n4\n4\nC 2 . 3\n6\n1\nC 3\n. 2\n−−\n−\n\n−\n\n\n\n\n\n=\n\n\n ⇒ n = 10 So T\n3 = 10\nC\n2 11\n.8.2\n44\n45.4\n2 .360 3\n3\n−\n== 5. Let a 2i 3j 4k, b 2i – 2j – 2k\n= + +\n= and c i 4j 3k\n= − + +\n. If d is a vector perpendicular to both b and c and a.d\n= 18, Then 2\nad is equal to (1) 640 (2) 760 (3) 680 (4) 720 Official Ans. by NTA (4) Allen Ans. (4) 2 Sol. (\n)\na\nb c\n=   i j k\nb c 1 2 2\n1 4 3\n =\n− −\n− = 2i j 2k\n−+ (\n)\nd\n2i j 2k\n=  − + a.d 18\n= 2\n= So (\n)\nd 2 2i j 2k\n= − + i j k\nd a 4 2 4\n2 3 4\n = − = 20i 8j 16k\n− − + 2\nd a 720\n= 6. The straight lines l\n1 and l\n2 pass through the origin and trisect the line segment of the line L: 9x + 5y = 45 between the axes. If m\n1 and m\n2 are the slopes of the lines l\n1 and l\n2\n,then the point of intersection of the line y = (m\n1 + m\n2\n)x with L lies on (1) 6x + y = 10 (2) 6x– y = 15 (3) y –x = 5 (4) y –2x = 5 Official Ans. by NTA (3) Allen Ans. (3) Sol. 1\nL\nm = 3.3 9\n10 10\n= 2\nL\nm = 6.3 18\n55\n= y =(m\n1 + m\n2\n)x y = 9\nx\n2 Point of intersection with L is 10 45\n,\n77\n\n\n 7. From the top A of a vertical wall AB of height 30 m, the angles of depression of the top P and bottom Q of a vertical tower PQ are 15° and 60° respectively. B and Q are on the same horizontal level. If C is a point on AB such that CB = PQ, then the area (in m\n2\n) of the quadrilateral BCPQ is equal to (1) (\n)\n600 3 1− (2) (\n)\n300 3 1\n+ (3) (\n)\n200 3 3\n− (4) (\n)\n300 3 –1 Official Ans. by NTA (1) Allen Ans. (1) Sol. 30\ntan 60\n3\nBQ\n = = BQ = 10 3m = CP AC\ntan15 2 3\nCP\n = − = (\n)\nAC 10 3 2 3\n=− Area = (\n)\n(\n)\n10 3 60 20 3 600 3 1\n−\n=\n− 8. The sum of the first 20 terms of the series 5 +11 + 19+ 29 + 41 + ... is (1) 3450 (2) 3250 (3) 3420 (4) 3520 Official Ans. by NTA (4) Allen Ans. (4) Sol. S\n20 = 5 + 11 + 19 + 29 +....... Let T\nr = ar\n2 + br + c T\n1 = a+ b +c = 5 T\n2 = 4a +2b + c = 11 T\n3 = 9a + 3b +c = 19 a = 1, b = 3, c = 1 Hence S\n20 = 202020\n2\nr 1r 1r 1\nr 3 r 1 3520\n===\n++ =\n   3 9. The mean and variance of a set of 15 numbers are 12 and 14 respectively. The mean and variance of another set of 15 numbers are 14 and 2\n respectively. If the variance of all the 30 numbers in the two sets is 13, then 2\n\nis equal to (1) 9 (2) 12 (3) 11 (4) 10 Official Ans. by NTA (4) Allen Ans. (4) Sol. Combine var. = (\n)\n(\n)\n2\n22\n1 2\n1\n2\n12\n2\n12\n12\nn n m m\nnn\nnn\nnn\n−\n + \n+\n+\n+ 13 =\n(\n)\n2\n2\n15.15 12 14\n15.14 15.\n30\n30 30\n−\n+\n+\n 2\n14\n4\n13\n24\n+\n=+ 2\n10\n= 10. Let A = [a\nij\n]\n2×2 where a\nij ≠ 0 for all i, j and A\n2 = I. Let a be the sum of all diagonal elements of A and b = |A|, then 3a\n2 + 4b\n2 is equal to (1) 7 (2) 14 (3) 3 (4) 4 Official Ans. by NTA (4) Allen Ans. (4) Sol. Let pq\nA\nrs\n\n=\n\n 2\n2\n2\np qr pq qs\nA\npr rs qs s\n\n++\n=\n\n++\n 2\np qr 1 + = (1) (\n)\npq qs 0 q p s 0\n+ =  + =\n(3) 2\ns qr 1\n + = (2) ()\npr rs 0 r p s 0+ =  + = (4) Equation (1) – equation (2) 22\np s p s 0=  + = Now 3a\n2 + 4b\n2 = ()()\n22\n3 p s 4 ps qr+ + − = 3.0 + 4 (\n)\n(\n)\n22\n22\np qr 4 p qr 4− − =+ = 11. Let (\n)\n(\n)\n(\n)\n22\n2\nx xsec x tan x\nI x\ndx\nx tan x 1\n+\n=\n+\n\n. If I(0) = 0 the I 4\n\n\n\n is equal to (1) (\n)\n(\n)\n2\n2\ne\nx4\nlog\n16\n4 4\n+\n\n−\n+ (2) (\n)\n(\n)\n2\n2\ne\nx4\nlog\n16\n4 4\n+\n\n+\n+ (3) (\n)\n(\n)\n2\n2\ne\nx4\nlog\n32\n4 4\n+\n\n−\n+ (4) (\n)\n(\n)\n2\n2\ne\nx4\nlog\n32\n4 4\n+\n\n+\n+ Official Ans. by NTA (3) Allen Ans. (3) Sol. (\n)\n(\n)\n(\n)\n22\n2\nx xsec x tan x\nI x\ndx\nx tan x 1\n+\n=\n+\n Let xtan x + 1= t 2\n1\n2x\nI x\ndx\nx tan x 1\nx tan x 1\n−\n\n=+\n\n\n++\n 2\n1\nx cos x\nI x\n2\ndx\nx tan x 1\nxsin x cos x\n−\n\n=+\n\n\n++\n 2\n1\nI x\n2ln xsin x cos x C\nx tan x 1\n−\n\n=\n+\n+\n+\n\n\n+ As I(0) = 0 ⇒ C = 0 (\n)\n(\n)\n2\n2\n4\nI\nln\n4\n32\n4 4\n\n+\n\n\n=−\n\n\n\n+\n 12. If the equation of the plane passing through the line of intersection of the planes 2x – y + z = 3, 4x– 3y +5z + 9 = 0 and parallel to the line x 1 y 3 z 2\n245\n++−\n==\n− is ax + by + cz + 6 = 0. then a + b + c is equal to (1) 14 (2) 12 (3) 13 (4) 15 Official Ans. by NTA (1) Allen Ans. (1) 4 Sol. Equation of family of plane (\n)\n2x y z 3\n− + − + (\n)\n4x 3y 5z 9 0\n − + + = (\n)\n(\n)\n(\n)\nx 2 4 y 1 3 z 1 5 3 9 0\n+  − +  + +  − +  = Parallel to the line ()()()\n2 2 4 1 3 4 1 5 5 0− +  − +  + +  = 53\n= 3\n5\n= equation of plane 11x 7y 10z 6 0\n− + + = a + b + c = 14 13. Statement (\n)\n(\n)\nP Q R Q\n is logically equivalent to (1) (\n)\nP R Q\n (2) (\n)\n(\n)\nP R Q R\n   (3) (\n)\n(\n)\nP R Q R\n   (4) (\n)\nP R Q\n Official Ans. by NTA (1) Allen Ans. (1) Sol. (\n)\n(\n)\nP Q R Q\n We known that PQ\n ≡ ~ P Q\n ⇒\n(\n)\n(\n)\n~ P Q ~ R Q\n   ⇒\n(\n)\n~ P ~ R Q\n ⇒\n(\n)\n~ P R Q\n ⇒\n(\n)\nP R Q\n 14. The sum of all the roots of the equation 2\nx 8x 15 – 2x 7 0− ++ =\nis: (1) 93\n+ (2) 11 3\n+ (3) 9 – 3 (4) 11 – 3 Official Ans. by NTA (1) Allen Ans. (1) Sol. For x 3or x 5 2\nx 8x 15 2x 7 0− + − + = x 5 3=+ For 3 x 5\n, 2\nx 8x 15 2x 7 0− + + − = x = 4 Hence sum = 93+ 15. Let a\n1\n, a\n2, a\n3\n. ...a\nn be n positive consecutive terms of an arithmetic progression. If d > 0 is its common difference, then n\n1\n2\n2\n3\nn 1\nn\nd\n1\n1\n1\nlim\n.........\nn\na\na\na\na\na\na\n→\n−\n\n+\n+\n+\n\n+\n+\n+\n\n(1) 1 (2) d (3) 1\nd (4) 0 Official Ans. by NTA (1) Allen Ans. (1) Sol.\nn\n1\n2\n2\n3\nn 1\nn\nd\n1\n1\n1\nlim\n.........\nn\na\na\na\na\na\na\n→\n−\n\n+\n+\n+\n\n+\n+\n+\n\nOn rationalising each term n1\nn\naa\nd\nlim\nnd\n→\n\n−\n\n (\n)\n(\n)\nn\nn1\nn 1 d\nd\nlim\nn\na\na d\n→\n\n−\n\n\n+\n = 1 16. If the system of equations x + y + az = b 2x + 5y + 2z = 6 x + 2y + 3z = 3 has infinitely many solutions, then 2a + 3b is equal to (1) 23 (2) 28 (3) 25 (4) 20 Official Ans. by NTA (1) Allen Ans. (1) Sol. 1 1 a\n2 5 2\n1 2 3\n=\n= 0 ⇒ 11 – 4 – a = 0 a = 7 1\nb 1 a\n6 5 2\n3 2 3\n= = 0 ⇒ 11b –12 –21 = 0 b = 3 2a + 3b = 23 5 17. If 2x\ny + 3y\nx = 20, then dy\ndx at (2, 2) is equal to (1) e\ne\n3 log 8\n2 log 4\n\n+\n−\n\n+\n (2) e\ne\n2 log 8\n3 log 4\n\n+\n−\n\n+\n (3) e\ne\n3 log 16\n4 log 8\n\n+\n−\n\n+\n (4) e\ne\n3 log 4\n2 log 8\n\n+\n−\n\n+\n Official Ans. by NTA (2) Allen Ans. (2) Sol. 2x\ny + 3y\nx = 20 (\n)\nyx\ny\nxy'\n2x\nln x y' 3y\nln y 0\nxy\n\n\n+\n+\n+\n=\n\n\n\n (\n)\n12ln 2 8\ny'\n12 8ln 2\n−+\n=\n+\n= e\ne\n2 log 8\n3 log 4\n\n+\n−\n\n+\n 18. One vertex of a rectangular parallelopiped is at the origin O and the lengths of its edges along x, y and z axes are 3, 4 and 5 units respectively. Let P be the vertex (3, 4, 5). Then the shortest distance between the diagonal OP and an edge parallel to z axis, not passing through O or P is: (1) 12\n5 (2) 12\n55 (3) 12 5 (4) 12\n5 Official Ans. by NTA (4) Allen Ans. (4) Sol Equation of OP is x y z\n3 4 5\n== a\n1 = (0, 0, 0) a\n2 = (3, 0, 5) b\n1 = (3, 4, 5) b\n2 = (0, 0, 1) Equation of edge parallel to z axis x 3 y 0 z 5\n001\n−−−\n== S.D = (\n)\n(\n)\n2\n1\n1\n2\n12\na a . b b\nbb\n−\n ()\n3 0 5\n3 4 5\n0 0 13 4\n12\n5\n4i 3j\ni j k\n3 4 5\n0 0 1\n==\n− 19. Let the position vectors of the points A, B, C and D be 5i 5j 2 k, i 2j 3k, 2i j 4k\n+ +  + + − + + and i 5j 6k− + +\n. Let the set \nS\n=  \n: The points A, B, C and D are coplanar}. Then (\n)\n2\nS\n2\n\n+\n is equal to (1) 41 (2) 25 (3) 13 (4) 37\n2 Official Ans. by NTA (1) Allen Ans. (1) Sol. Since A, B, C, D are coplanner Hence BA CA DA 0\n\n=\n 4 3 2 3\n7 5\n2 4 0\n6 0 2 6\n−\n−  − =\n− 2,3\n= Hence (\n)\n2\nS\n2 41\n\n + =\n 20. Let \n\n\n\n\n\nA x : x 3 x 4 3\n= \n+ + + \n, x3\nx\n3x\nr\nr1\n3\nB x :3\n3\n10\n−\n\n−\n=\n\n\n\n= \n\n\n\n\n\n\n\n\n, where [t] denotes greatest integer function. Then, (1) AB\n =  (2) A = B (3) B C,A B\n (4) A B,A B\n Official Ans. by NTA (2) Allen Ans. (2) Sol. \n\n\n\nx 3 x 4 3\n+ + +  \n\n2 x 4\n− \n\nx2\n− ⇒\n(\n)\nx\n, 1\n − −\n........(A) x3\nx3x\n1\n3.\n10\n33\n1\n1\n10\n−\n−\n\n\n\n\n\n−\n 3x\n27 3\n−\n 3x 3−  + x1− .................(B) A = B 6 SECTION-B 21. Let a\n and [t] be the greatest integer < t. Then the number of points, where the function f(x) = [a + 13 sin x], x ∈ (0, 휋) is not differentiable, is ____ Official Ans. by NTA (25) Allen Ans. (25) Sol. f(x) = [a + 13 sin x], x ∈ (0, 휋) For [n sin x]; Total number of non differentiable points are = 2n –1 for ()\nx 0, So number of non differentiable points for [13 sin x] ⇒ 25 Points 22. A circle passing through the point P\n(\n)\n,\n in the first quadrant touches the two coordinate axes at the points A and B. The point P is above the line AB. The point Q on the line segment AB is the foot of perpendicular from P on AB. If PQ is equal to 11 units, then the value of  is______ Official Ans. by NTA (121) Allen Ans. (121) Sol. Let equation of circle is (\n)\n(\n)\n22\n2\nx a\ny a a\n− + − = which is passing through P ()\n, then (\n)\n(\n)\n22\n2\na\na a\n − + − = 2\n2\n2\n2 a 2 a a 0\n + −  −  + = Here equation of AB is x + y = a Let Q (\n)\n', '\n\nbe foot of perpendicular of P on AB ()\na\n''\n112\n−  +−\n −  −\n== PQ\n2 = ()()()()\n222\n11\n''aa\n44\n − +  − =  + − +  + − (\n)\n2\n1\n121\na\n2\n=  + − 2\n2\n2\n242\n2 a 2 a a 2\n=  + −  −  + +  242 = 2\n 121\n  = 23. The number of ways of giving 20 distinct oranges to 3 children such that each child gets atleast one orange is_________ Official Ans. by NTA (171) Allen Ans. (Bonus) Sol. 20 distinct oranges distributed among 3 children so that each child gets at least one orange = 3\n20 – 3\nC\n1 2\n20 + 3\nC\n2 1\n20 Bonus 24. If the area of the region ()\n\n22\nS x,y : 2y y x 2y,x y=−   is equal to n2\nn 1 n 1\n+\n−\n+−\n, then the natural number n is equal to ________ Official Ans. by NTA (5) Allen Ans. (5) Sol. 22\nx y 2y 0\n+ −  & 2\nx 2y 0\n−\n, xy\n Hence required area = 2\n2\n0\n1\nx\n1\n2 2\ndx\n2\n2\n4 2\n\n\n  −\n− −\n\n\n = 7\n64\n\n− ⇒ n = 5 25. Let the point (p, p + 1) lie inside the region ()\n\n2\nE x,y :3 x y 9 x ,0 x 3=−   − \nIf the set of all values of p is the interval (a, b). then b\n2 + b – a\n2 is equal to _________ Official Ans. by NTA (3) Allen Ans. (3) 7 Sol. 2\n3 x y 9 x\n−   − Points (p, p + 1) lies on y = x + 1 So point of intersection between y = x + 1 & y = 3 – x is x = 1, y = 2 and point of intersection between 2\nx 1 9 x\n+ = −\nis 1 17\nx\n2\n−+\n= Hence 1 17\np 1,\n2\n\n−+\n\n\n Hence b\n2 + b – a\n2 = 3 26. Let y = y(x) be a solution of the differential equation (xcos x)dy + (xysinx + ycos x – l)dx = 0, 0x\n2\n\n\n. If y3\n33\n\n\n=\n\n\n, then y\"\n2y'\n6 6\n6\n \n\n \n \n+\n \n \n \n \nis equal to ______ Official Ans. by NTA (2) Allen Ans. (2) Sol. (xcos x)dy + (xysinx + ycos x – l)dx = 0, 0x\n2\n\n dy xsin x cos x\n1\ny\ndx\nx cos x\nx cos x\n+\n\n+=\n\n IF = x secx xsecx\ny.xsecx\ndx tan x c\nx cos x\n=\n=\n+\n Since 33\ny\n3\n\n\n=\n\n\n Hence\nc3\n= Hence\ny\"y'2 2\n6 66\n \n   \n+= − =\n   \n    27. The coefficient of x\n18 in the expansion of 15\n4\n3\n1\nx\nx\n\n−\n\n is _____ Official Ans. by NTA (5005) Allen Ans. (5005) Sol. 15\n4\n3\n1\nx\nx\n\n−\n\n (\n)\nr\n15 r\n15\n4\nr 1\nr\n3\n1\nT\nC x\nx\n−\n+\n−\n\n=\n\n 60 –7r = 18 r = 6 Hence coeff. of x\n18 = 15\nC\n6 = 5005 28. Let A={1, 2, 3, 4,.....10} and B = {0, 1, 2, 3, 4}. The number of elements in the relation R = {(a, b) ∈ A × A: 2(a – b)\n2 + 3(a – b) ∈ B} is______ Official Ans. by NTA (18) Allen Ans. (18) Sol. \n\nA 1,2,3,......10\n= \n\nB 0,1,2,3,4\n= R = {(a, b) ∈ A × A: 2(a – b)\n2 + 3(a – b) ∈ B} Now (\n)\n(\n)\n(\n)\n(\n)\n(\n)\n2\n2 a b 3 a b a b 2 a b 3\n− + − = −\n− + ⇒ a = b or a– b = –2 When a = b ⇒ 10 order pairs When a– b = –2 ⇒8 order pairs Total = 18 29. Let the image of the point P(l, 2, 3) in the plane 2x – y + z = 9 be Q. If the coordinates of the point R are (6, 10, 7), then the square of the area of the triangle PQR is_ Official Ans. by NTA (594) Allen Ans. (594) Sol. Let Q (\n)\n,,\n  \nbe the image of P, about the plane 2x – y + z = 9 123\n2\n211\n −  −  −\n===\n− ⇒\n5=\n, 0=\n, 5\n= Then area of triangle PQR is =\n1\nPQ PR\n2\n = 12i 3j 21k− − + = 144 9 441++\n= 594 Square of area = 594 8 30. Let the tangent to the curve x\n2 + 2x – 4y + 9 = 0 at the point P(1, 3) on it meet the y-axis at A. Let the line passing through P and parallel to the line x – 3y = 6 meet the parabola y\n2 = 4x at B. If B lies on the line 2x – 3y = 8. then (AB)\n2 is equal to Official Ans. by NTA (292) Allen Ans. (292) Sol. Equation of tangent at P (1, 3) to the curve x\n2 + 2x – 4y + 9 = 0 is y –x = 2 Then the point A is (0, 2) Equation of line passing through P and parallel to the line x – 3y = 6. The possible coordinate of B are (4, 4) or (16, 8) But (4, 4) does not satisfy 2x –3y = 8 Thus the point B is (16, 8) Then (AB)\n2 = 292",
    "questions": [],
    "mathEquations": [
      {
        "equation": "N-A 1",
        "type": "mathematical",
        "position": 156
      },
      {
        "equation": "I = 2\n1\n15\n18\n4x 3 dx\n9x\n",
        "type": "mathematical",
        "position": 529
      },
      {
        "equation": "s = 1\n9\n= p Probability of failure\n8\nq\n9\n= P(at least 4 success) = P (4 success) + P (5 success) = 5455\n45\n10\n41\nC p q C p\n3\n+=\n= 11\n123\n3 k = 123 3",
        "type": "mathematical",
        "position": 845
      },
      {
        "equation": "C\n=\n",
        "type": "mathematical",
        "position": 1167
      },
      {
        "equation": "n = 8 So (\n)\n(\n)\n22\nn 3n ",
        "type": "mathematical",
        "position": 1223
      },
      {
        "equation": "n = 10 So T\n3 = 10\nC\n2 11\n",
        "type": "mathematical",
        "position": 1615
      },
      {
        "equation": "k\n= + +\n= and c i 4j 3k\n= ",
        "type": "mathematical",
        "position": 1702
      },
      {
        "equation": "d\n= 18",
        "type": "mathematical",
        "position": 1789
      },
      {
        "equation": "c\n= ",
        "type": "mathematical",
        "position": 1907
      },
      {
        "equation": "k\n= ",
        "type": "mathematical",
        "position": 1972
      },
      {
        "equation": "k\n= ",
        "type": "mathematical",
        "position": 2013
      },
      {
        "equation": "x + 5y = 45 between the axes",
        "type": "mathematical",
        "position": 2184
      },
      {
        "equation": "y = (m\n1 + m\n2\n)x with L lies on (1) 6x + y = 10 (2) 6x",
        "type": "mathematical",
        "position": 2313
      },
      {
        "equation": "y = 15 (3) y ",
        "type": "mathematical",
        "position": 2370
      },
      {
        "equation": "x = 5 (4) y ",
        "type": "mathematical",
        "position": 2384
      },
      {
        "equation": "x = 5 Official Ans",
        "type": "mathematical",
        "position": 2398
      },
      {
        "equation": "m = 3",
        "type": "mathematical",
        "position": 2453
      },
      {
        "equation": "m = 6",
        "type": "mathematical",
        "position": 2475
      },
      {
        "equation": "y =(m\n1 + m\n2\n)x y = 9\nx\n2 Point of intersection with L is 10 45\n",
        "type": "mathematical",
        "position": 2491
      },
      {
        "equation": "B = PQ",
        "type": "mathematical",
        "position": 2805
      },
      {
        "equation": "Q = 10 3m = CP AC\ntan15 2 3\nCP\n",
        "type": "mathematical",
        "position": 3012
      },
      {
        "equation": "a = (\n)\n(\n)\n10 3 60 20 3 600 3 1\n",
        "type": "mathematical",
        "position": 3073
      },
      {
        "equation": "r = ar\n2 + br + c T\n1 = a+ b +c = 5 T\n2 = 4a +2b + c = 11 T\n3 = 9a + 3b +c = 19 a = 1",
        "type": "mathematical",
        "position": 3308
      },
      {
        "equation": "b = 3",
        "type": "mathematical",
        "position": 3395
      },
      {
        "equation": "c = 1 Hence S\n20 = 202020\n2\nr 1r 1r 1\nr 3 r 1 3520\n===\n++ =\n",
        "type": "mathematical",
        "position": 3402
      },
      {
        "equation": "A = ",
        "type": "mathematical",
        "position": 3946
      },
      {
        "equation": "b = ",
        "type": "mathematical",
        "position": 4054
      },
      {
        "equation": "r+ + ",
        "type": "mathematical",
        "position": 4421
      },
      {
        "equation": "x + 1= t 2\n1\n2x\nI x\ndx\nx tan x 1\nx tan x 1\n",
        "type": "mathematical",
        "position": 4859
      },
      {
        "equation": "C = 0 (\n)\n(\n)\n2\n2\n4\nI\nln\n4\n32\n4 4\n",
        "type": "mathematical",
        "position": 5056
      },
      {
        "equation": "y + z = 3",
        "type": "mathematical",
        "position": 5213
      },
      {
        "equation": "y +5z + 9 = 0 and parallel to the line x 1 y 3 z 2\n245\n++",
        "type": "mathematical",
        "position": 5229
      },
      {
        "equation": "x + by + cz + 6 = 0",
        "type": "mathematical",
        "position": 5297
      },
      {
        "equation": "a + b + c is equal to (1) 14 (2) 12 (3) 13 (4) 15 Official Ans",
        "type": "mathematical",
        "position": 5323
      },
      {
        "equation": "a + b + c = 14 13",
        "type": "mathematical",
        "position": 5677
      },
      {
        "equation": "x = 4 Hence sum = 93+ 15",
        "type": "mathematical",
        "position": 6262
      },
      {
        "equation": "x + y + az = b 2x + 5y + 2z = 6 x + 2y + 3z = 3 has infinitely many solutions",
        "type": "mathematical",
        "position": 6790
      },
      {
        "equation": "a + 3b is equal to (1) 23 (2) 28 (3) 25 (4) 20 Official Ans",
        "type": "mathematical",
        "position": 6875
      },
      {
        "equation": "a = 0 a = 7 1\nb 1 a\n6 5 2\n3 2 3\n",
        "type": "mathematical",
        "position": 7003
      },
      {
        "equation": "b = 3 2a + 3b = 23 5 17",
        "type": "mathematical",
        "position": 7060
      },
      {
        "equation": "y + 3y\nx = 20",
        "type": "mathematical",
        "position": 7091
      },
      {
        "equation": "y + 3y\nx = 20 (\n)\nyx\ny\nxy",
        "type": "mathematical",
        "position": 7344
      },
      {
        "equation": "D = (\n)\n(\n)\n2\n1\n1\n2\n12\na a ",
        "type": "mathematical",
        "position": 8026
      },
      {
        "equation": "k\n+ + ",
        "type": "mathematical",
        "position": 8211
      },
      {
        "equation": "S\n= ",
        "type": "mathematical",
        "position": 8263
      },
      {
        "equation": "A = B (3) B C",
        "type": "mathematical",
        "position": 8745
      },
      {
        "equation": "A = B 6 SECTION-B 21",
        "type": "mathematical",
        "position": 9002
      },
      {
        "equation": "a + 13 sin x",
        "type": "mathematical",
        "position": 9123
      },
      {
        "equation": "a + 13 sin x",
        "type": "mathematical",
        "position": 9235
      },
      {
        "equation": "e = 2n ",
        "type": "mathematical",
        "position": 9320
      },
      {
        "equation": "x + y = a Let Q (\n)\n",
        "type": "mathematical",
        "position": 9940
      },
      {
        "equation": "e = 3\n20 ",
        "type": "mathematical",
        "position": 10455
      },
      {
        "equation": "a = 2\n2\n0\n1\nx\n1\n2 2\ndx\n2\n2\n4 2\n",
        "type": "mathematical",
        "position": 10746
      },
      {
        "equation": "n = 5 25",
        "type": "mathematical",
        "position": 10813
      },
      {
        "equation": "p + 1) lie inside the region ()\n",
        "type": "mathematical",
        "position": 10841
      },
      {
        "equation": "p + 1) lies on y = x + 1 So point of intersection between y = x + 1 ",
        "type": "mathematical",
        "position": 11086
      },
      {
        "equation": "y = 3 ",
        "type": "mathematical",
        "position": 11156
      },
      {
        "equation": "x = 1",
        "type": "mathematical",
        "position": 11169
      },
      {
        "equation": "y = 2 and point of intersection between 2\nx 1 9 x\n+ = ",
        "type": "mathematical",
        "position": 11176
      },
      {
        "equation": "y = y(x) be a solution of the differential equation (xcos x)dy + (xysinx + ycos x ",
        "type": "mathematical",
        "position": 11313
      },
      {
        "equation": "x = 0",
        "type": "mathematical",
        "position": 11400
      },
      {
        "equation": "y + (xysinx + ycos x ",
        "type": "mathematical",
        "position": 11567
      },
      {
        "equation": "x = 0",
        "type": "mathematical",
        "position": 11593
      },
      {
        "equation": "x\n+\n",
        "type": "mathematical",
        "position": 11647
      },
      {
        "equation": "F = x secx xsecx\ny",
        "type": "mathematical",
        "position": 11664
      },
      {
        "equation": "x\n=\n=\n+\n",
        "type": "mathematical",
        "position": 11706
      },
      {
        "equation": "r = 18 r = 6 Hence coeff",
        "type": "mathematical",
        "position": 12022
      },
      {
        "equation": "B = ",
        "type": "mathematical",
        "position": 12107
      },
      {
        "equation": "R = ",
        "type": "mathematical",
        "position": 12167
      },
      {
        "equation": "R = ",
        "type": "mathematical",
        "position": 12312
      },
      {
        "equation": "a = b or a",
        "type": "mathematical",
        "position": 12426
      },
      {
        "equation": "b = ",
        "type": "mathematical",
        "position": 12438
      },
      {
        "equation": "a = b ",
        "type": "mathematical",
        "position": 12450
      },
      {
        "equation": "b = ",
        "type": "mathematical",
        "position": 12481
      },
      {
        "equation": "l = 18 29",
        "type": "mathematical",
        "position": 12507
      },
      {
        "equation": "y + z = 9 be Q",
        "type": "mathematical",
        "position": 12574
      },
      {
        "equation": "y + z = 9 123\n2\n211\n",
        "type": "mathematical",
        "position": 12800
      },
      {
        "equation": "s =\n1\nPQ PR\n2\n",
        "type": "mathematical",
        "position": 12884
      },
      {
        "equation": "a = 594 8 30",
        "type": "mathematical",
        "position": 12951
      },
      {
        "equation": "y + 9 = 0 at the point P(1",
        "type": "mathematical",
        "position": 13006
      },
      {
        "equation": "y-axis at A",
        "type": "mathematical",
        "position": 13052
      },
      {
        "equation": "y = 6 meet the parabola y\n2 = 4x at B",
        "type": "mathematical",
        "position": 13126
      },
      {
        "equation": "y = 8",
        "type": "mathematical",
        "position": 13193
      },
      {
        "equation": "y + 9 = 0 is y ",
        "type": "mathematical",
        "position": 13330
      },
      {
        "equation": "x = 2 Then the point A is (0",
        "type": "mathematical",
        "position": 13346
      },
      {
        "equation": "y = 6",
        "type": "mathematical",
        "position": 13444
      },
      {
        "equation": "y = 8 Thus the point B is (16",
        "type": "mathematical",
        "position": 13535
      },
      {
        "equation": "log",
        "type": "mathematical",
        "position": 252
      },
      {
        "equation": "log",
        "type": "mathematical",
        "position": 271
      },
      {
        "equation": "log",
        "type": "mathematical",
        "position": 289
      },
      {
        "equation": "log",
        "type": "mathematical",
        "position": 307
      },
      {
        "equation": "log",
        "type": "mathematical",
        "position": 573
      },
      {
        "equation": "exp",
        "type": "mathematical",
        "position": 1357
      },
      {
        "equation": "tan",
        "type": "mathematical",
        "position": 2993
      },
      {
        "equation": "tan",
        "type": "mathematical",
        "position": 3030
      },
      {
        "equation": "tan",
        "type": "mathematical",
        "position": 4508
      },
      {
        "equation": "tan",
        "type": "mathematical",
        "position": 4523
      },
      {
        "equation": "log",
        "type": "mathematical",
        "position": 4605
      },
      {
        "equation": "log",
        "type": "mathematical",
        "position": 4646
      },
      {
        "equation": "log",
        "type": "mathematical",
        "position": 4687
      },
      {
        "equation": "log",
        "type": "mathematical",
        "position": 4728
      },
      {
        "equation": "tan",
        "type": "mathematical",
        "position": 4819
      },
      {
        "equation": "tan",
        "type": "mathematical",
        "position": 4834
      },
      {
        "equation": "tan",
        "type": "mathematical",
        "position": 4855
      },
      {
        "equation": "tan",
        "type": "mathematical",
        "position": 4884
      },
      {
        "equation": "tan",
        "type": "mathematical",
        "position": 4894
      },
      {
        "equation": "cos",
        "type": "mathematical",
        "position": 4927
      },
      {
        "equation": "tan",
        "type": "mathematical",
        "position": 4944
      },
      {
        "equation": "sin",
        "type": "mathematical",
        "position": 4953
      },
      {
        "equation": "cos",
        "type": "mathematical",
        "position": 4959
      },
      {
        "equation": "ln",
        "type": "mathematical",
        "position": 4993
      },
      {
        "equation": "sin",
        "type": "mathematical",
        "position": 4997
      },
      {
        "equation": "cos",
        "type": "mathematical",
        "position": 5003
      },
      {
        "equation": "tan",
        "type": "mathematical",
        "position": 5013
      },
      {
        "equation": "ln",
        "type": "mathematical",
        "position": 5078
      },
      {
        "equation": "sin",
        "type": "mathematical",
        "position": 5156
      },
      {
        "equation": "log",
        "type": "mathematical",
        "position": 5729
      },
      {
        "equation": "sin",
        "type": "mathematical",
        "position": 6657
      },
      {
        "equation": "log",
        "type": "mathematical",
        "position": 7149
      },
      {
        "equation": "log",
        "type": "mathematical",
        "position": 7157
      },
      {
        "equation": "log",
        "type": "mathematical",
        "position": 7188
      },
      {
        "equation": "log",
        "type": "mathematical",
        "position": 7196
      },
      {
        "equation": "log",
        "type": "mathematical",
        "position": 7227
      },
      {
        "equation": "log",
        "type": "mathematical",
        "position": 7236
      },
      {
        "equation": "log",
        "type": "mathematical",
        "position": 7267
      },
      {
        "equation": "log",
        "type": "mathematical",
        "position": 7275
      },
      {
        "equation": "ln",
        "type": "mathematical",
        "position": 7374
      },
      {
        "equation": "ln",
        "type": "mathematical",
        "position": 7385
      },
      {
        "equation": "ln",
        "type": "mathematical",
        "position": 7427
      },
      {
        "equation": "ln",
        "type": "mathematical",
        "position": 7441
      },
      {
        "equation": "log",
        "type": "mathematical",
        "position": 7461
      },
      {
        "equation": "log",
        "type": "mathematical",
        "position": 7469
      },
      {
        "equation": "tan",
        "type": "mathematical",
        "position": 7513
      },
      {
        "equation": "tan",
        "type": "mathematical",
        "position": 7694
      },
      {
        "equation": "sin",
        "type": "mathematical",
        "position": 7763
      },
      {
        "equation": "sin",
        "type": "mathematical",
        "position": 9130
      },
      {
        "equation": "sin",
        "type": "mathematical",
        "position": 9242
      },
      {
        "equation": "sin",
        "type": "mathematical",
        "position": 9268
      },
      {
        "equation": "sin",
        "type": "mathematical",
        "position": 9391
      },
      {
        "equation": "sin",
        "type": "mathematical",
        "position": 9426
      },
      {
        "equation": "sin",
        "type": "mathematical",
        "position": 9825
      },
      {
        "equation": "cos",
        "type": "mathematical",
        "position": 11367
      },
      {
        "equation": "sin",
        "type": "mathematical",
        "position": 11381
      },
      {
        "equation": "cos",
        "type": "mathematical",
        "position": 11389
      },
      {
        "equation": "cos",
        "type": "mathematical",
        "position": 11560
      },
      {
        "equation": "sin",
        "type": "mathematical",
        "position": 11574
      },
      {
        "equation": "cos",
        "type": "mathematical",
        "position": 11582
      },
      {
        "equation": "sin",
        "type": "mathematical",
        "position": 11614
      },
      {
        "equation": "cos",
        "type": "mathematical",
        "position": 11620
      },
      {
        "equation": "cos",
        "type": "mathematical",
        "position": 11635
      },
      {
        "equation": "cos",
        "type": "mathematical",
        "position": 11643
      },
      {
        "equation": "tan",
        "type": "mathematical",
        "position": 11692
      },
      {
        "equation": "cos",
        "type": "mathematical",
        "position": 11702
      },
      {
        "equation": "exp",
        "type": "mathematical",
        "position": 11845
      },
      {
        "equation": "tan",
        "type": "mathematical",
        "position": 12973
      },
      {
        "equation": "sin",
        "type": "mathematical",
        "position": 13081
      },
      {
        "equation": "tan",
        "type": "mathematical",
        "position": 13285
      },
      {
        "equation": "sin",
        "type": "mathematical",
        "position": 13399
      }
    ],
    "chemicalEquations": [],
    "topics": [
      {
        "name": "Geometry",
        "confidence": 0.5714285714285714,
        "matchedKeywords": [
          "triangle",
          "circle",
          "area",
          "coordinate"
        ],
        "possibleSubtopics": [
          "Coordinate Geometry",
          "Conic Sections",
          "3D Geometry",
          "Lines and Planes"
        ]
      },
      {
        "name": "Trigonometry",
        "confidence": 0.6666666666666666,
        "matchedKeywords": [
          "sin",
          "cos",
          "tan",
          "angle"
        ],
        "possibleSubtopics": [
          "Trigonometric Functions",
          "Trigonometric Identities",
          "Inverse Trigonometric Functions"
        ]
      }
    ],
    "subtopics": [
      {
        "name": "Coordinate Geometry",
        "parentTopic": "Geometry",
        "confidence": 0.8,
        "matchedKeywords": [
          "coordinates",
          "distance",
          "slope",
          "equation of line"
        ]
      }
    ],
    "tags": [],
    "wordCount": 4162,
    "characterCount": 13586
  },
  "images": []
}
